PrettifyLogging/__init__.py
PrettifyLogging/prettify_logging.py
Prettify_Logging-1.0.2.dist-info/LICENSE
Prettify_Logging-1.0.2.dist-info/METADATA
Prettify_Logging-1.0.2.dist-info/WHEEL
Prettify_Logging-1.0.2.dist-info/top_level.txt
Prettify_Logging-1.0.2.dist-info/RECORD
