Metadata-Version: 2.1
Name: Prettify-Logging
Version: 1.0.2
Summary: Prettify-Logging is a wrapper tool that colors the stream formatting of the logging module.
Home-page: https://github.com/johnjkenny/Prettify-Logging
Author: John J Kenny
Author-email: johnjkenny88@gmail.com
License: UNKNOWN
Project-URL: Bug Tracker, https://github.com/johnjkenny/Prettify-Logging/issues
Platform: UNKNOWN
Classifier: Programming Language :: Python :: 3
Classifier: License :: OSI Approved :: GNU Affero General Public License v3 or later (AGPLv3+)
Classifier: Operating System :: OS Independent
License-File: LICENSE
Requires-Dist: Color-Fi
